owping.py
owping_parser-0.2.3.dist-info/METADATA
owping_parser-0.2.3.dist-info/RECORD
owping_parser-0.2.3.dist-info/WHEEL
owping_parser-0.2.3.dist-info/top_level.txt
